{"data":{"type":"Precios mercado peninsular en tiempo real","id":"mer13","attributes":{"title":"Precios mercado peninsular en tiempo real","last-update":"2020-10-18T14:31:14.000+02:00","description":null},"meta":{"cache-control":{"cache":"MISS"}}},"included":[{"type":"Precio mercado spot (\u20ac\/MWh)","id":"600","groupId":null,"attributes":{"title":"Precio mercado spot (\u20ac\/MWh)","description":null,"color":"#df4a32","type":null,"magnitude":"price","composite":false,"last-update":"2020-10-18T14:31:14.000+02:00","values":[{"value":42.3,"percentage":1,"datetime":"2020-10-18T00:00:00.000+02:00"},{"value":40.4,"percentage":1,"datetime":"2020-10-18T01:00:00.000+02:00"},{"value":40.4,"percentage":1,"datetime":"2020-10-18T02:00:00.000+02:00"},{"value":40.4,"percentage":1,"datetime":"2020-10-18T03:00:00.000+02:00"},{"value":39.99,"percentage":1,"datetime":"2020-10-18T04:00:00.000+02:00"},{"value":39.65,"percentage":1,"datetime":"2020-10-18T05:00:00.000+02:00"},{"value":39.35,"percentage":1,"datetime":"2020-10-18T06:00:00.000+02:00"},{"value":39.36,"percentage":1,"datetime":"2020-10-18T07:00:00.000+02:00"},{"value":38.99,"percentage":1,"datetime":"2020-10-18T08:00:00.000+02:00"},{"value":40.28,"percentage":1,"datetime":"2020-10-18T09:00:00.000+02:00"},{"value":40,"percentage":1,"datetime":"2020-10-18T10:00:00.000+02:00"},{"value":38.55,"percentage":1,"datetime":"2020-10-18T11:00:00.000+02:00"},{"value":39.68,"percentage":1,"datetime":"2020-10-18T12:00:00.000+02:00"},{"value":36.1,"percentage":1,"datetime":"2020-10-18T13:00:00.000+02:00"},{"value":32.69,"percentage":1,"datetime":"2020-10-18T14:00:00.000+02:00"},{"value":31.5,"percentage":1,"datetime":"2020-10-18T15:00:00.000+02:00"},{"value":32.5,"percentage":1,"datetime":"2020-10-18T16:00:00.000+02:00"},{"value":39.05,"percentage":1,"datetime":"2020-10-18T17:00:00.000+02:00"},{"value":46.56,"percentage":1,"datetime":"2020-10-18T18:00:00.000+02:00"},{"value":49.58,"percentage":1,"datetime":"2020-10-18T19:00:00.000+02:00"},{"value":49.6,"percentage":1,"datetime":"2020-10-18T20:00:00.000+02:00"},{"value":45.65,"percentage":1,"datetime":"2020-10-18T21:00:00.000+02:00"},{"value":43.17,"percentage":1,"datetime":"2020-10-18T22:00:00.000+02:00"},{"value":40.4,"percentage":1,"datetime":"2020-10-18T23:00:00.000+02:00"},{"value":37.78,"percentage":1,"datetime":"2020-10-19T00:00:00.000+02:00"}]}}]}